aifleet/__init__.py
aifleet/cli.py
aifleet/config.py
aifleet/state.py
aifleet/tmux.py
aifleet/updater.py
aifleet/utils.py
aifleet/worktree.py
aifleet/commands/__init__.py
aifleet/commands/attach.py
aifleet/commands/base.py
aifleet/commands/create.py
aifleet/commands/fanout.py
aifleet/commands/init.py
aifleet/commands/kill.py
aifleet/commands/list.py
aifleet/commands/logs.py
aifleet/commands/multi.py
aifleet/commands/prompt.py
aifleet/commands/update.py
ai_fleet-0.1.3.dist-info/METADATA
ai_fleet-0.1.3.dist-info/WHEEL
ai_fleet-0.1.3.dist-info/entry_points.txt
ai_fleet-0.1.3.dist-info/licenses/LICENSE
ai_fleet-0.1.3.dist-info/RECORD
