Metadata-Version: 2.4
Name: ai-fleet
Version: 0.1.3
Summary: Spin up and command a fleet of AI developer agents from your terminal
Project-URL: Homepage, https://github.com/nachoal/ai-fleet
Project-URL: Repository, https://github.com/nachoal/ai-fleet
Project-URL: Issues, https://github.com/nachoal/ai-fleet/issues
Project-URL: Documentation, https://github.com/nachoal/ai-fleet#readme
Author-email: Ignacio Alonso <ignacio.alley@gmail.com>
License-Expression: MIT
License-File: LICENSE
Keywords: agents,ai,automation,claude,cli,development,tmux
Classifier: Development Status :: 3 - Alpha
Classifier: Intended Audience :: Developers
Classifier: License :: OSI Approved :: MIT License
Classifier: Operating System :: OS Independent
Classifier: Programming Language :: Python :: 3
Classifier: Programming Language :: Python :: 3.9
Classifier: Programming Language :: Python :: 3.10
Classifier: Programming Language :: Python :: 3.11
Classifier: Programming Language :: Python :: 3.12
Classifier: Topic :: Software Development :: Libraries :: Python Modules
Classifier: Topic :: Software Development :: Version Control :: Git
Classifier: Topic :: Utilities
Requires-Python: >=3.9
Requires-Dist: click>=8.1.0
Requires-Dist: libtmux>=0.37.0
Requires-Dist: psutil>=5.9.0
Requires-Dist: rich>=14.0.0
Requires-Dist: toml>=0.10.0
Provides-Extra: dev
Requires-Dist: black>=23.0.0; extra == 'dev'
Requires-Dist: lefthook>=1.5.0; extra == 'dev'
Requires-Dist: mypy>=1.0.0; extra == 'dev'
Requires-Dist: pyyaml>=6.0.0; extra == 'dev'
Requires-Dist: ruff>=0.1.0; extra == 'dev'
Provides-Extra: test
Requires-Dist: pytest-cov>=4.0.0; extra == 'test'
Requires-Dist: pytest-mock>=3.10.0; extra == 'test'
Requires-Dist: pytest>=7.0.0; extra == 'test'
Provides-Extra: update
Requires-Dist: packaging>=21.0; extra == 'update'
Requires-Dist: requests>=2.28.0; extra == 'update'
